README.md
setup.cfg
setup.py
shapley/__init__.py
shapley/forest.py
shapley/indices.py
shapley/kriging.py
shapley/model.py
shapley/plots.py
shapley/shapley.py
shapley/sobol.py
shapley/utils.py
shapley_effects.egg-info/PKG-INFO
shapley_effects.egg-info/SOURCES.txt
shapley_effects.egg-info/dependency_links.txt
shapley_effects.egg-info/requires.txt
shapley_effects.egg-info/top_level.txt