Metadata-Version: 1.0
Name: shapley-effects
Version: 0.1
Summary: Estimation of Shapley effects for Sensitivity Analysis of Model Output.
Home-page: https://gitlab.com/CEMRACS17/shapley-effects
Author: Nazih BENOUMECHIARA & Kevin ELIE-DIT-COSAQUE
Author-email: nazih.benoumechiara@gmail.com
License: MIT
Keywords: sensitivity analysis,shapley,effects,depedencies
Platform: UNKNOWN
